README.md
setup.py
cantrips/__init__.py
cantrips/console.py
cantrips/decorators.py
cantrips/entropy.py
cantrips/features.py
cantrips/functions.py
cantrips/iteration.py
cantrips/patterns/__init__.py
cantrips/patterns/singleton.py
cantrips/types/__init__.py
cantrips/types/arguments.py
cantrips/types/events.py
cantrips/types/exception.py
cantrips/types/flags.py
cantrips/types/frozen.py
python_cantrips.egg-info/PKG-INFO
python_cantrips.egg-info/SOURCES.txt
python_cantrips.egg-info/dependency_links.txt
python_cantrips.egg-info/top_level.txt