Metadata-Version: 1.2
Name: python-cantrips
Version: 1.0.0
Summary: Python library with quick utilities to make use of in a wide variety of situations
Home-page: https://github.com/luismasuelli/python-cantrips
Author: Luis y Anita
Author-email: luismasuelli@hotmail.com
License: LGPL
Platform: UNKNOWN
Requires-Python: >=3.6
